setup.py
src/langacore/__init__.py
src/langacore.thingsweforget.egg-info/PKG-INFO
src/langacore.thingsweforget.egg-info/SOURCES.txt
src/langacore.thingsweforget.egg-info/dependency_links.txt
src/langacore.thingsweforget.egg-info/namespace_packages.txt
src/langacore.thingsweforget.egg-info/requires.txt
src/langacore.thingsweforget.egg-info/top_level.txt
src/langacore/thingsweforget/__init__.py
src/langacore/thingsweforget/__main__.py