Metadata-Version: 1.0
Name: langacore.thingsweforget
Version: 0.1.0
Summary: Synchronization of images from thingsweforget.blogspot.com for offline use.
Home-page: UNKNOWN
Author: Lukasz Langa
Author-email: lukasz@langa.pl
License: BSD
Keywords: http,downloader,sync,www,crawler,blogspot
Platform: UNKNOWN
Classifier: Programming Language :: Python
Classifier: Programming Language :: Python :: 3
Classifier: Development Status :: 3 - Alpha
Classifier: Environment :: Other Environment
Classifier: Intended Audience :: Developers
Classifier: License :: OSI Approved :: BSD License
Classifier: Operating System :: POSIX
Classifier: Topic :: Software Development :: Libraries :: Python Modules
